csv_converter_and_book_recommender_pkg/__init__.py
csv_converter_and_book_recommender_pkg/download_csv.py
csv_converter_and_book_recommender_pkg/fetch_best_books.py
csv_converter_and_book_recommender_pkg/recommend_book_download_csv.py
csv_converter_and_book_recommender_pkg_Preeti_Rawat-0.0.5.dist-info/LICENSE
csv_converter_and_book_recommender_pkg_Preeti_Rawat-0.0.5.dist-info/METADATA
csv_converter_and_book_recommender_pkg_Preeti_Rawat-0.0.5.dist-info/WHEEL
csv_converter_and_book_recommender_pkg_Preeti_Rawat-0.0.5.dist-info/top_level.txt
csv_converter_and_book_recommender_pkg_Preeti_Rawat-0.0.5.dist-info/RECORD
