Metadata-Version: 2.1
Name: csv-converter-and-book-recommender-pkg-Preeti-Rawat
Version: 0.0.5
Summary: A model to csv converter and book recommender package
Home-page: https://github.com/pypa/bookrecommenderandcsvconverter
Author: Preeti_Rawat
Author-email: x20233507@student.ncirl.ie
License: UNKNOWN
Platform: UNKNOWN
Classifier: Programming Language :: Python :: 3
Classifier: License :: OSI Approved :: MIT License
Classifier: Operating System :: OS Independent
Requires-Python: >=3.6
License-File: LICENSE
